_extension.cpython-39-x86_64-linux-gnu.so
laser/core/__init__.py
laser/core/__main__.py
laser/core/_extension.c
laser/core/cli.py
laser/core/distributions.py
laser/core/extension.py
laser/core/laserframe.py
laser/core/migration.py
laser/core/propertyset.py
laser/core/random.py
laser/core/sortedqueue.py
laser/core/utils.py
laser/core/data/us-pyramid-2023.csv
laser/core/demographics/__init__.py
laser/core/demographics/kmestimator.py
laser/core/demographics/pyramid.py
laser/core/demographics/spatialpops.py
laser_core-1.0.0.dist-info/METADATA
laser_core-1.0.0.dist-info/WHEEL
laser_core-1.0.0.dist-info/top_level.txt
laser_core-1.0.0.dist-info/RECORD
laser_core-1.0.0.dist-info/licenses/AUTHORS.rst
laser_core-1.0.0.dist-info/licenses/LICENSE
