Metadata-Version: 2.4
Name: laser-core
Version: 1.0.0
Summary: Core functionality for the Light Agent Spatial modeling for ERadication toolkit (LASER).
Author-email: Christopher Lorton <christopher.lorton@gatesfoundation.org>, Jonathan Bloedow <jonathan.bloedow@gatesfoundation.org>, Katherine Rosenfeld <katherine.rosenfeld@gatesfoundation.org>, Kevin McCarthy <kevin.mccarthy@gatesfoundation.org>
Maintainer-email: Christopher Lorton <christopher.lorton@gatesfoundation.org>, Jonathan Bloedow <jonathan.bloedow@gatesfoundation.org>
License-Expression: MIT
Project-URL: Homepage, https://github.com/InstituteforDiseaseModeling/laser
Project-URL: Issues, https://github.com/InstituteforDiseaseModeling/laser/issues
Project-URL: Documentation, https://docs.idmod.org/projects/laser/en/latest/
Project-URL: Changelog, https://docs.idmod.org/projects/laser/en/latest/changelog.html
Keywords: spatial modeling,disease eradication,agent-based modeling
Classifier: Programming Language :: Python :: 3
Classifier: Operating System :: OS Independent
Classifier: Programming Language :: Python
Classifier: Programming Language :: Python :: 3
Classifier: Programming Language :: Python :: 3.9
Classifier: Programming Language :: Python :: 3.10
Classifier: Programming Language :: Python :: 3.11
Classifier: Programming Language :: Python :: 3.12
Classifier: Programming Language :: Python :: 3.13
Classifier: Programming Language :: Python :: Implementation :: CPython
Requires-Python: <3.14,>=3.9
License-File: LICENSE
License-File: AUTHORS.rst
Requires-Dist: click
Requires-Dist: numpy
Requires-Dist: numba
Requires-Dist: matplotlib
Requires-Dist: pandas
Requires-Dist: h5py
Requires-Dist: geopandas
Requires-Dist: shapely
Provides-Extra: dev
Requires-Dist: pytest>=6.0; extra == "dev"
Requires-Dist: black; extra == "dev"
Requires-Dist: flake8; extra == "dev"
Requires-Dist: tox; extra == "dev"
Requires-Dist: tox-uv; extra == "dev"
Requires-Dist: uv; extra == "dev"
Provides-Extra: docs
Requires-Dist: sphinx>=1.3; extra == "docs"
Requires-Dist: sphinx-rtd-theme; extra == "docs"
Requires-Dist: furo; extra == "docs"
Provides-Extra: test
Requires-Dist: pytest>=6.0; extra == "test"
Requires-Dist: pytest-cov; extra == "test"
Requires-Dist: scipy; extra == "test"
Requires-Dist: uv; extra == "test"
Dynamic: license-file
